ensync_sdk/__init__.py
ensync_sdk/ensync_pb2.py
ensync_sdk/ensync_pb2_grpc.py
ensync_sdk/grpc_client.py
ensync_sdk-0.4.4.dist-info/METADATA
ensync_sdk-0.4.4.dist-info/WHEEL
ensync_sdk-0.4.4.dist-info/top_level.txt
ensync_sdk-0.4.4.dist-info/RECORD
