Metadata-Version: 2.4
Name: ensync-sdk
Version: 0.4.4
Summary: Python SDK for EnSync Engine - high-performance real-time messaging via gRPC
Home-page: https://github.com/EnSync-engine/Python-SDK
Author: EnSync Team
Author-email: dev@ensync.cloud
Keywords: ensync,grpc,messaging,real-time,pubsub
Classifier: Development Status :: 4 - Beta
Classifier: Intended Audience :: Developers
Classifier: License :: OSI Approved :: MIT License
Classifier: Programming Language :: Python :: 3
Classifier: Programming Language :: Python :: 3.7
Classifier: Programming Language :: Python :: 3.8
Classifier: Programming Language :: Python :: 3.9
Classifier: Programming Language :: Python :: 3.10
Classifier: Programming Language :: Python :: 3.11
Requires-Python: >=3.7
Requires-Dist: ensync-core>=0.1.0
Requires-Dist: grpcio>=1.50.0
Requires-Dist: grpcio-tools>=1.50.0
Provides-Extra: dev
Requires-Dist: python-dotenv>=0.19.0; extra == "dev"
Dynamic: author
Dynamic: author-email
Dynamic: classifier
Dynamic: description
Dynamic: description-content-type
Dynamic: home-page
Dynamic: keywords
Dynamic: provides-extra
Dynamic: requires-dist
Dynamic: requires-python
Dynamic: summary
